flowdb/__init__.py
flowdb/cli.py
flowdb/client.py
flowdb/core/__init__.py
flowdb/core/engine.py
flowdb/core/vectorizer.py
flowdb/server/__init__.py
flowdb/server/app.py
flowdb-0.1.2.dist-info/METADATA
flowdb-0.1.2.dist-info/WHEEL
flowdb-0.1.2.dist-info/entry_points.txt
flowdb-0.1.2.dist-info/licenses/LICENSE
flowdb-0.1.2.dist-info/RECORD
