Metadata-Version: 2.4
Name: flowdb
Version: 0.1.2
Summary: The AI-Native Database: JSON + Vectors + MCP
Project-URL: Homepage, https://github.com/yourusername/flowdb
Project-URL: Issues, https://github.com/yourusername/flowdb/issues
Author-email: Your Name <your.email@example.com>
License-Expression: MIT
License-File: LICENSE
Keywords: agent,ai,database,mcp,rag,vector
Classifier: License :: OSI Approved :: MIT License
Classifier: Operating System :: OS Independent
Classifier: Programming Language :: Python :: 3
Requires-Python: >=3.10
Requires-Dist: fastapi>=0.100.0
Requires-Dist: fastmcp
Requires-Dist: lmdb>=1.4.0
Requires-Dist: numpy
Requires-Dist: openai
Requires-Dist: pydantic>=2.0.0
Requires-Dist: python-dotenv
Requires-Dist: requests
Requires-Dist: usearch>=2.9.0
Requires-Dist: uvicorn[standard]>=0.20.0
